pruebas/__init__.py
pruebas/test_bf.py
pruebas/test_calib_ecs.py
pruebas/test_calib_valid_modelos.py
pruebas/test_clima.py
pruebas/test_conectado.py
pruebas/test_config.py
pruebas/test_datos.py
pruebas/test_envolt_externas.py
pruebas/test_geog.py
pruebas/test_mds.py
pruebas/test_modelo.py
pruebas/test_sintaxis.py
pruebas/test_unidades.py
pruebas/recursos/__init__.py
pruebas/recursos/bf/__init__.py
pruebas/recursos/bf/prueba_bf.py
pruebas/recursos/bf/variantes.py
pruebas/recursos/bf/_prbs_arch/arch_clase.py
pruebas/recursos/bf/_prbs_arch/arch_clase_no_identificada.py
pruebas/recursos/bf/_prbs_arch/arch_instancia.py
pruebas/recursos/bf/_prbs_arch/arch_instancia_no_identificada.py
pruebas/recursos/bf/_prbs_arch/arch_múltiples.py
pruebas/recursos/bf/_prbs_arch/arch_múltiples_no_identificada.py
pruebas/recursos/bf/_prbs_arch/arch_vacío.py
pruebas/recursos/bf/_prbs_arch/no_python.txt
pruebas/recursos/datos/__init__.py
pruebas/recursos/datos/datos.csv
pruebas/recursos/datos/datos2.csv
pruebas/recursos/mds/Modelo con extensión no reconocida.வணக்கம்
pruebas/recursos/mds/__init__.py
pruebas/recursos/mds/prueba_para_calib.mdl
pruebas/recursos/mds/prueba_para_calib.vpm
pruebas/recursos/mds/prueba_senc_mdl.mdl
pruebas/recursos/mds/prueba_senc_py.py
pruebas/recursos/mds/prueba_senc_vpm.vpm
pruebas/recursos/mds/prueba_senc_xml.xmile
pruebas/recursos/mod/__init__.py
pruebas/recursos/mod/prueba_mod.py
tinamit/__init__.py
tinamit/config.py
tinamit/cositas.py
tinamit/versión.txt
tinamit/_local/act_trads_mnsj.py
tinamit/_local/_fuente/ar/LC_MESSAGES/tinamit.mo
tinamit/_local/_fuente/ar/LC_MESSAGES/tinamit.po
tinamit/_local/_fuente/cak/LC_MESSAGES/tinamit.mo
tinamit/_local/_fuente/cak/LC_MESSAGES/tinamit.po
tinamit/_local/_fuente/de/LC_MESSAGES/tinamit.mo
tinamit/_local/_fuente/de/LC_MESSAGES/tinamit.po
tinamit/_local/_fuente/fr/LC_MESSAGES/tinamit.mo
tinamit/_local/_fuente/fr/LC_MESSAGES/tinamit.po
tinamit/_local/_fuente/hi/LC_MESSAGES/tinamit.mo
tinamit-2.0.3.dist-info/LICENSE.md
tinamit-2.0.3.dist-info/METADATA
tinamit-2.0.3.dist-info/WHEEL
tinamit-2.0.3.dist-info/top_level.txt
tinamit-2.0.3.dist-info/RECORD
