Metadata-Version: 2.1
Name: tinamit
Version: 2.0.3
Summary: Conexión de modelos socioeconómicos (dinámicas de los sistemas) con modelos biofísicos.
Home-page: https://tinamit.readthedocs.io
Author: Julien Jean Malard
Author-email: julien.malard@mail.mcgill.ca
License: GNU GPL 3
Download-URL: https://github.com/julienmalard/Tinamit
Platform: UNKNOWN
Classifier: License :: OSI Approved :: GNU General Public License v3 (GPLv3)
Classifier: Programming Language :: Python :: 3 :: Only
Requires-Dist: numpy
Requires-Dist: scipy
Requires-Dist: matplotlib
Requires-Dist: pillow
Requires-Dist: pandas
Requires-Dist: python-dateutil
Requires-Dist: regex
Requires-Dist: lark-parser
Requires-Dist: pint
Requires-Dist: pyshp
Requires-Dist: taqdir
Requires-Dist: pysd
Requires-Dist: lxml
Requires-Dist: xarray
Requires-Dist: chardet
Requires-Dist: spotpy
Requires-Dist: ennikkai
